docs/_build/man/secrets-to-paper.1
secrets_to_paper/__init__.py
secrets_to_paper/build/__init__.py
secrets_to_paper/build/ecc.py
secrets_to_paper/build/rsa.py
secrets_to_paper/export/__init__.py
secrets_to_paper/export/ecc.py
secrets_to_paper/export/gnupg.py
secrets_to_paper/export/qr.py
secrets_to_paper/export/rsa.py
secrets_to_paper/parse/__init__.py
secrets_to_paper/parse/hid/utils.py
secrets_to_paper/parse/pdf.py
secrets_to_paper/parse/scanner.py
secrets_to_paper/parse/webcam.py
secrets_to_paper/stp.py
secrets_to_paper/templates/ecc_key.html
secrets_to_paper/templates/gpg_key.html
secrets_to_paper/templates/main.css
secrets_to_paper/templates/rsa_key.html
secrets_to_paper-0.0.13.dist-info/entry_points.txt
secrets_to_paper-0.0.13.dist-info/METADATA
secrets_to_paper-0.0.13.dist-info/WHEEL
secrets_to_paper-0.0.13.dist-info/RECORD
