Metadata-Version: 2.1
Name: secrets-to-paper
Version: 0.0.13
Summary: A command line tool to help with key-to-paper and paper-to-key.
Home-page: https://salsa.debian.org/jvacanti/secrets-to-paper
License: MIT
Keywords: paperkey,gpg,secrets-to-paper
Author: Jared Vacanti
Author-email: jaredvacanti@gmail.com
Requires-Python: >=3.10,<4.0
Classifier: License :: OSI Approved :: MIT License
Classifier: Programming Language :: Python :: 3
Classifier: Programming Language :: Python :: 3.10
Classifier: Programming Language :: Python :: 3.11
Requires-Dist: click (>=8.1.7,<9.0.0)
Requires-Dist: cryptography (>=41.0.5,<42.0.0)
Requires-Dist: jinja2 (>=3.1.2,<4.0.0)
Requires-Dist: opencv-contrib-python (>=4.8.1.78,<5.0.0.0)
Requires-Dist: opencv-python (>=4.8.1.78,<5.0.0.0)
Requires-Dist: pdfplumber (>=0.10.3,<0.11.0)
Requires-Dist: pillow (>=10.1.0,<11.0.0)
Requires-Dist: pyzbar (>=0.1.9,<0.2.0)
Requires-Dist: qrcode (>=7.4.2,<8.0.0)
Requires-Dist: weasyprint (>=60.1,<61.0)
Project-URL: Repository, https://salsa.debian.org/jvacanti/secrets-to-paper.git
